LICENSE
README.md
setup.py
ccprompt/__init__.py
ccprompt/config.py
ccprompt/main.py
ccprompt/parser_factory.py
ccprompt/utils.py
ccprompt.egg-info/PKG-INFO
ccprompt.egg-info/SOURCES.txt
ccprompt.egg-info/dependency_links.txt
ccprompt.egg-info/entry_points.txt
ccprompt.egg-info/requires.txt
ccprompt.egg-info/top_level.txt
ccprompt/parsers/__init__.py
ccprompt/parsers/base_parser.py
ccprompt/parsers/esprima_adapter.py
ccprompt/parsers/javascript_parser.py
ccprompt/parsers/js_parser_interface.py
ccprompt/parsers/python_parser.py