Metadata-Version: 2.1
Name: ccprompt
Version: 0.2.0
Summary: Extract code context for AI prompts based on a function or class name.
Home-page: https://github.com/Samk13/ccprompt
Author: Sam Arbid
Author-email: samarbid13@gmail.com
License: UNKNOWN
Platform: UNKNOWN
Classifier: Programming Language :: Python :: 3
Classifier: Operating System :: OS Independent
Requires-Python: >=3.9
Provides-Extra: dev
Provides-Extra: javascript
License-File: LICENSE
